{
  "name": "Happy",
  "widgets": [
    [
      { "widget": "./widgets/random" },
      { "widget": "./widgets/gauge" },
      { "widget": "./widgets/health" },
      { "widget": "vudash-widget-time" }
    ],
    [
      { "widget": "./widgets/github" },
      { "widget": "vudash-widget-pluck", "options": { "path": "rates.GBP", "description": "EUR -> GBP" } },
      { "widget": "vudash-widget-pluck", "options": { "path": "rates.USD", "description": "EUR -> USD" } }
    ],
    [
      { "widget": "./widgets/dial" },
      { "widget": "vudash-widget-travis" },
      { "widget": "vudash-widget-travis", "options": { "user": "vudash", "repo": "vudash-widget-travis" } }
    ]
  ]
}
